{
"meta":{"test_sets":[],"test_metrics":[],"learn_metrics":[{"best_value":"Min","name":"Logloss"}],"launch_mode":"Train","parameters":"","iteration_count":400,"learn_sets":["learn"],"name":"experiment"},
"iterations":[
{"learn":[0.6851551497],"iteration":0,"passed_time":0.003219428192,"remaining_time":1.284551849},
{"learn":[0.6770212524],"iteration":1,"passed_time":0.005714237567,"remaining_time":1.137133276},
{"learn":[0.6694327733],"iteration":2,"passed_time":0.0079187729,"remaining_time":1.047917614},
{"learn":[0.6631564984],"iteration":3,"passed_time":0.008592857263,"remaining_time":0.8506928691},
{"learn":[0.6568794371],"iteration":4,"passed_time":0.009684402415,"remaining_time":0.7650677908},
{"learn":[0.6481633919],"iteration":5,"passed_time":0.01170136248,"remaining_time":0.7683894697},
{"learn":[0.6417220081],"iteration":6,"passed_time":0.01362616242,"remaining_time":0.76501169},
{"learn":[0.6391358516],"iteration":7,"passed_time":0.01403118774,"remaining_time":0.6875281995},
{"learn":[0.6329398527],"iteration":8,"passed_time":0.01589601131,"remaining_time":0.6905933801},
{"learn":[0.6274126558],"iteration":9,"passed_time":0.01773897919,"remaining_time":0.6918201884},
{"learn":[0.6219134642],"iteration":10,"passed_time":0.01948279395,"remaining_time":0.6889824404},
{"learn":[0.6171822874],"iteration":11,"passed_time":0.02104884434,"remaining_time":0.6805793003},
{"learn":[0.6109574493],"iteration":12,"passed_time":0.02263210978,"remaining_time":0.6737404989},
{"learn":[0.6064156532],"iteration":13,"passed_time":0.0235115206,"remaining_time":0.6482462108},
{"learn":[0.6027732023],"iteration":14,"passed_time":0.02502879864,"remaining_time":0.6424058317},
{"learn":[0.5990970284],"iteration":15,"passed_time":0.02748805249,"remaining_time":0.6597132599},
{"learn":[0.5933476612],"iteration":16,"passed_time":0.02890018932,"remaining_time":0.6511042652},
{"learn":[0.5901015176],"iteration":17,"passed_time":0.03050614296,"remaining_time":0.6474081451},
{"learn":[0.5871892731],"iteration":18,"passed_time":0.03130159389,"remaining_time":0.6276793301},
{"learn":[0.583498744],"iteration":19,"passed_time":0.03262282748,"remaining_time":0.619833722},
{"learn":[0.5788921424],"iteration":20,"passed_time":0.03388314339,"remaining_time":0.611510064},
{"learn":[0.5755054351],"iteration":21,"passed_time":0.03525196978,"remaining_time":0.6056929353},
{"learn":[0.5703081118],"iteration":22,"passed_time":0.03663072009,"remaining_time":0.6004252814},
{"learn":[0.5682078851],"iteration":23,"passed_time":0.03755224656,"remaining_time":0.5883185295},
{"learn":[0.5638392482],"iteration":24,"passed_time":0.03895418703,"remaining_time":0.5843128055},
{"learn":[0.5605046539],"iteration":25,"passed_time":0.04027280853,"remaining_time":0.5793088612},
{"learn":[0.5579310973],"iteration":26,"passed_time":0.04198183817,"remaining_time":0.57997132},
{"learn":[0.5545434397],"iteration":27,"passed_time":0.04329978632,"remaining_time":0.5752685897},
{"learn":[0.550509799],"iteration":28,"passed_time":0.04482880276,"remaining_time":0.5734995112},
{"learn":[0.5461861342],"iteration":29,"passed_time":0.04633696371,"remaining_time":0.5714892191},
{"learn":[0.5438931818],"iteration":30,"passed_time":0.04766974609,"remaining_time":0.5674237519},
{"learn":[0.5402903352],"iteration":31,"passed_time":0.04898924477,"remaining_time":0.5633763149},
{"learn":[0.5371313379],"iteration":32,"passed_time":0.0502553664,"remaining_time":0.5589005899},
{"learn":[0.5355142461],"iteration":33,"passed_time":0.05092668175,"remaining_time":0.5482107506},
{"learn":[0.532140177],"iteration":34,"passed_time":0.05226067413,"remaining_time":0.5450041731},
{"learn":[0.5295934802],"iteration":35,"passed_time":0.05366837465,"remaining_time":0.5426468993},
{"learn":[0.5290630522],"iteration":36,"passed_time":0.05432037382,"remaining_time":0.5329269107},
{"learn":[0.5261699208],"iteration":37,"passed_time":0.05588881575,"remaining_time":0.5324145079},
{"learn":[0.5237060174],"iteration":38,"passed_time":0.05730917203,"remaining_time":0.5304772077},
{"learn":[0.5205099415],"iteration":39,"passed_time":0.05863908861,"remaining_time":0.5277517975},
{"learn":[0.5173429546],"iteration":40,"passed_time":0.05990757308,"remaining_time":0.5245565545},
{"learn":[0.5150773149],"iteration":41,"passed_time":0.06123308105,"remaining_time":0.5219391194},
{"learn":[0.5124238045],"iteration":42,"passed_time":0.06259060937,"remaining_time":0.5196476173},
{"learn":[0.5112874376],"iteration":43,"passed_time":0.06394686108,"remaining_time":0.5173882397},
{"learn":[0.5091021945],"iteration":44,"passed_time":0.06532007437,"remaining_time":0.5153028089},
{"learn":[0.5075964121],"iteration":45,"passed_time":0.06663994753,"remaining_time":0.5128378571},
{"learn":[0.506681374],"iteration":46,"passed_time":0.06795123674,"remaining_time":0.510357161},
{"learn":[0.5053072505],"iteration":47,"passed_time":0.0693530562,"remaining_time":0.5085890788},
{"learn":[0.503552038],"iteration":48,"passed_time":0.07066401959,"remaining_time":0.5061851199},
{"learn":[0.5016495401],"iteration":49,"passed_time":0.07197175716,"remaining_time":0.5038023001},
{"learn":[0.4993919592],"iteration":50,"passed_time":0.0735659225,"remaining_time":0.5034217049},
{"learn":[0.4971987822],"iteration":51,"passed_time":0.07504221453,"remaining_time":0.5022055895},
{"learn":[0.4946648113],"iteration":52,"passed_time":0.07643009066,"remaining_time":0.5004007823},
{"learn":[0.4926876813],"iteration":53,"passed_time":0.07795481176,"remaining_time":0.4994882383},
{"learn":[0.490111388],"iteration":54,"passed_time":0.07935325,"remaining_time":0.4977612954},
{"learn":[0.4883648192],"iteration":55,"passed_time":0.08067247824,"remaining_time":0.4955595092},
{"learn":[0.4871916421],"iteration":56,"passed_time":0.08196949704,"remaining_time":0.4932550436},
{"learn":[0.4857096946],"iteration":57,"passed_time":0.08319523615,"remaining_time":0.4905650132},
{"learn":[0.4836649402],"iteration":58,"passed_time":0.08447122956,"remaining_time":0.4882150725},
{"learn":[0.4826238355],"iteration":59,"passed_time":0.08578415113,"remaining_time":0.4861101897},
{"learn":[0.4814141387],"iteration":60,"passed_time":0.08706506183,"remaining_time":0.4838533764},
{"learn":[0.4801789129],"iteration":61,"passed_time":0.0883740331,"remaining_time":0.4817810191},
{"learn":[0.478814365],"iteration":62,"passed_time":0.08968706569,"remaining_time":0.4797546212},
{"learn":[0.4777920883],"iteration":63,"passed_time":0.09099835514,"remaining_time":0.4777413645},
{"learn":[0.4751862479],"iteration":64,"passed_time":0.09246875764,"remaining_time":0.4765697509},
{"learn":[0.4744733486],"iteration":65,"passed_time":0.09381273206,"remaining_time":0.4747492804},
{"learn":[0.4725621321],"iteration":66,"passed_time":0.09509941355,"remaining_time":0.4726582793},
{"learn":[0.4715356056],"iteration":67,"passed_time":0.09679650794,"remaining_time":0.4725947152},
{"learn":[0.46932216],"iteration":68,"passed_time":0.09822635404,"remaining_time":0.4712017853},
{"learn":[0.4675695533],"iteration":69,"passed_time":0.09948769632,"remaining_time":0.4690134255},
{"learn":[0.4668782862],"iteration":70,"passed_time":0.1009739425,"remaining_time":0.467893339},
{"learn":[0.4658937521],"iteration":71,"passed_time":0.1023445836,"remaining_time":0.4662364363},
{"learn":[0.4650457945],"iteration":72,"passed_time":0.1036314931,"remaining_time":0.4642123047},
{"learn":[0.4648224833],"iteration":73,"passed_time":0.1040841477,"remaining_time":0.4585328667},
{"learn":[0.4636703513],"iteration":74,"passed_time":0.1055593238,"remaining_time":0.4574237363},
{"learn":[0.4616892802],"iteration":75,"passed_time":0.106917507,"remaining_time":0.4558062139},
{"learn":[0.4607712923],"iteration":76,"passed_time":0.1082094034,"remaining_time":0.4539173674},
{"learn":[0.4607207464],"iteration":77,"passed_time":0.1085251613,"remaining_time":0.4480141275},
{"learn":[0.4596028481],"iteration":78,"passed_time":0.1098776274,"remaining_time":0.4464647898},
{"learn":[0.4583308786],"iteration":79,"passed_time":0.1111950968,"remaining_time":0.4447803871},
{"learn":[0.4574413039],"iteration":80,"passed_time":0.1125360707,"remaining_time":0.4431976117},
{"learn":[0.4558896479],"iteration":81,"passed_time":0.1139527977,"remaining_time":0.4419145083},
{"learn":[0.4543126922],"iteration":82,"passed_time":0.1153562371,"remaining_time":0.4405774357},
{"learn":[0.4533815627],"iteration":83,"passed_time":0.1166633654,"remaining_time":0.43887647},
{"learn":[0.4526221438],"iteration":84,"passed_time":0.1179655086,"remaining_time":0.4371662966},
{"learn":[0.4520492096],"iteration":85,"passed_time":0.1192584249,"remaining_time":0.4354319235},
{"learn":[0.4512399277],"iteration":86,"passed_time":0.1202430548,"remaining_time":0.4325985764},
{"learn":[0.4502847249],"iteration":87,"passed_time":0.1215931226,"remaining_time":0.4311028891},
{"learn":[0.4490394199],"iteration":88,"passed_time":0.1229646616,"remaining_time":0.4296855028},
{"learn":[0.4477703481],"iteration":89,"passed_time":0.1246736411,"remaining_time":0.4294314304},
{"learn":[0.4463199801],"iteration":90,"passed_time":0.1259617636,"remaining_time":0.4277163181},
{"learn":[0.4450207981],"iteration":91,"passed_time":0.1272811552,"remaining_time":0.4261151719},
{"learn":[0.4449123108],"iteration":92,"passed_time":0.1277418282,"remaining_time":0.4216853897},
{"learn":[0.4440756476],"iteration":93,"passed_time":0.1291948025,"remaining_time":0.4205703147},
{"learn":[0.4437011101],"iteration":94,"passed_time":0.130563239,"remaining_time":0.4191767146},
{"learn":[0.4429992738],"iteration":95,"passed_time":0.1315324528,"remaining_time":0.416519434},
{"learn":[0.4415060977],"iteration":96,"passed_time":0.1328182477,"remaining_time":0.4148858664},
{"learn":[0.441254859],"iteration":97,"passed_time":0.1332343832,"remaining_time":0.4105794257},
{"learn":[0.4400977999],"iteration":98,"passed_time":0.1345155082,"remaining_time":0.4089814946},
{"learn":[0.4392297558],"iteration":99,"passed_time":0.1358072736,"remaining_time":0.4074218209},
{"learn":[0.4372760006],"iteration":100,"passed_time":0.1371460406,"remaining_time":0.4060065955},
{"learn":[0.4367788883],"iteration":101,"passed_time":0.1384783612,"remaining_time":0.4045740357},
{"learn":[0.4351853274],"iteration":102,"passed_time":0.1397929251,"remaining_time":0.403092221},
{"learn":[0.434494985],"iteration":103,"passed_time":0.1411355411,"remaining_time":0.4016934632},
{"learn":[0.4340788582],"iteration":104,"passed_time":0.1423910922,"remaining_time":0.4000511637},
{"learn":[0.4327688821],"iteration":105,"passed_time":0.1437366468,"remaining_time":0.398665794},
{"learn":[0.4322048217],"iteration":106,"passed_time":0.1449534866,"remaining_time":0.3969287064},
{"learn":[0.4313242022],"iteration":107,"passed_time":0.146278452,"remaining_time":0.3954935924},
{"learn":[0.4300482158],"iteration":108,"passed_time":0.1476792887,"remaining_time":0.3942630552},
{"learn":[0.4293490959],"iteration":109,"passed_time":0.1489263938,"remaining_time":0.3926241291},
{"learn":[0.428498864],"iteration":110,"passed_time":0.15013351,"remaining_time":0.3908881477},
{"learn":[0.4277034979],"iteration":111,"passed_time":0.151585017,"remaining_time":0.3897900436},
{"learn":[0.4272269223],"iteration":112,"passed_time":0.1528688658,"remaining_time":0.3882598627},
{"learn":[0.4261417844],"iteration":113,"passed_time":0.1541118809,"remaining_time":0.3866315608},
{"learn":[0.4252245431],"iteration":114,"passed_time":0.1554631202,"remaining_time":0.3852781675},
{"learn":[0.424482301],"iteration":115,"passed_time":0.1567061889,"remaining_time":0.3836599797},
{"learn":[0.4228209001],"iteration":116,"passed_time":0.1579797164,"remaining_time":0.3821218782},
{"learn":[0.4214814037],"iteration":117,"passed_time":0.1592702157,"remaining_time":0.3806288206},
{"learn":[0.420966804],"iteration":118,"passed_time":0.1603737952,"remaining_time":0.3786977853},
{"learn":[0.4196677869],"iteration":119,"passed_time":0.1616545372,"remaining_time":0.3771939202},
{"learn":[0.4189005509],"iteration":120,"passed_time":0.1629490797,"remaining_time":0.3757255639},
{"learn":[0.4180969045],"iteration":121,"passed_time":0.1641820653,"remaining_time":0.374119788},
{"learn":[0.4177136955],"iteration":122,"passed_time":0.1655156153,"remaining_time":0.3727465483},
{"learn":[0.4172391354],"iteration":123,"passed_time":0.1668295647,"remaining_time":0.3713303215},
{"learn":[0.4162865568],"iteration":124,"passed_time":0.1680679501,"remaining_time":0.3697494903},
{"learn":[0.4153466769],"iteration":125,"passed_time":0.169328301,"remaining_time":0.3682218608},
{"learn":[0.4148615472],"iteration":126,"passed_time":0.1705078723,"remaining_time":0.3665247964},
{"learn":[0.4144157512],"iteration":127,"passed_time":0.1718552871,"remaining_time":0.3651924851},
{"learn":[0.4137206343],"iteration":128,"passed_time":0.1732134845,"remaining_time":0.3638825916},
{"learn":[0.4122816784],"iteration":129,"passed_time":0.1746103283,"remaining_time":0.3626522204},
{"learn":[0.4111752281],"iteration":130,"passed_time":0.1759342449,"remaining_time":0.3612695562},
{"learn":[0.4102651844],"iteration":131,"passed_time":0.1772196423,"remaining_time":0.3598095767},
{"learn":[0.4096840785],"iteration":132,"passed_time":0.1784316726,"remaining_time":0.3582049366},
{"learn":[0.4090911823],"iteration":133,"passed_time":0.1797931522,"remaining_time":0.3569028245},
{"learn":[0.4083176723],"iteration":134,"passed_time":0.181035918,"remaining_time":0.355366802},
{"learn":[0.4075686139],"iteration":135,"passed_time":0.1822786065,"remaining_time":0.3538349419},
{"learn":[0.4074997172],"iteration":136,"passed_time":0.1826964467,"remaining_time":0.3507238356},
{"learn":[0.4066699924],"iteration":137,"passed_time":0.1839318218,"remaining_time":0.3492038936},
{"learn":[0.4061947296],"iteration":138,"passed_time":0.1852386865,"remaining_time":0.3478222818},
{"learn":[0.4061876036],"iteration":139,"passed_time":0.1857611263,"remaining_time":0.3449849489},
{"learn":[0.4054810586],"iteration":140,"passed_time":0.1871026481,"remaining_time":0.343685006},
{"learn":[0.4048097767],"iteration":141,"passed_time":0.1884826134,"remaining_time":0.3424543257},
{"learn":[0.4045407833],"iteration":142,"passed_time":0.1896349672,"remaining_time":0.3408124934},
{"learn":[0.4032988391],"iteration":143,"passed_time":0.1910434965,"remaining_time":0.3396328826},
{"learn":[0.4022873618],"iteration":144,"passed_time":0.1924834698,"remaining_time":0.3385054124},
{"learn":[0.4016032732],"iteration":145,"passed_time":0.1937650556,"remaining_time":0.3370981104},
{"learn":[0.4004235859],"iteration":146,"passed_time":0.1951437959,"remaining_time":0.3358597304},
{"learn":[0.3996660755],"iteration":147,"passed_time":0.1964847481,"remaining_time":0.3345551117},
{"learn":[0.3991068515],"iteration":148,"passed_time":0.1977299701,"remaining_time":0.3330887416},
{"learn":[0.3976335666],"iteration":149,"passed_time":0.1990557425,"remaining_time":0.3317595709},
{"learn":[0.3972289567],"iteration":150,"passed_time":0.2003430372,"remaining_time":0.3303669952},
{"learn":[0.3969832847],"iteration":151,"passed_time":0.2011216186,"remaining_time":0.3281457988},
{"learn":[0.3961820235],"iteration":152,"passed_time":0.2023110553,"remaining_time":0.3266067363},
{"learn":[0.3960401136],"iteration":153,"passed_time":0.2027482402,"remaining_time":0.3238705655},
{"learn":[0.3953066414],"iteration":154,"passed_time":0.2040302818,"remaining_time":0.3224994777},
{"learn":[0.3945455807],"iteration":155,"passed_time":0.2052364325,"remaining_time":0.3210108304},
{"learn":[0.3938295432],"iteration":156,"passed_time":0.2065220784,"remaining_time":0.319648822},
{"learn":[0.3933541787],"iteration":157,"passed_time":0.2079364341,"remaining_time":0.3184849181},
{"learn":[0.3926298194],"iteration":158,"passed_time":0.2091812048,"remaining_time":0.3170608198},
{"learn":[0.3924458278],"iteration":159,"passed_time":0.2098070804,"remaining_time":0.3147106206},
{"learn":[0.3918138221],"iteration":160,"passed_time":0.2112545851,"remaining_time":0.3136015269},
{"learn":[0.3910995533],"iteration":161,"passed_time":0.2125592251,"remaining_time":0.3122783677},
{"learn":[0.390958195],"iteration":162,"passed_time":0.2138576315,"remaining_time":0.3109463722},
{"learn":[0.3902081631],"iteration":163,"passed_time":0.2151490953,"remaining_time":0.3096047957},
{"learn":[0.3897408016],"iteration":164,"passed_time":0.2164528115,"remaining_time":0.308281277},
{"learn":[0.3888155264],"iteration":165,"passed_time":0.2177480662,"remaining_time":0.3069460692},
{"learn":[0.3878680509],"iteration":166,"passed_time":0.2189972148,"remaining_time":0.3055470122},
{"learn":[0.3874159242],"iteration":167,"passed_time":0.2202407702,"remaining_time":0.304142016},
{"learn":[0.3874119413],"iteration":168,"passed_time":0.2206346509,"remaining_time":0.3015775406},
{"learn":[0.3869668043],"iteration":169,"passed_time":0.2219840852,"remaining_time":0.3003314094},
{"learn":[0.3868921796],"iteration":170,"passed_time":0.2224107948,"remaining_time":0.2978483744},
{"learn":[0.3864679079],"iteration":171,"passed_time":0.2236593651,"remaining_time":0.2964786933},
{"learn":[0.3854785344],"iteration":172,"passed_time":0.2249422011,"remaining_time":0.2951553737},
{"learn":[0.3845822834],"iteration":173,"passed_time":0.2263657984,"remaining_time":0.2940153473},
{"learn":[0.3840544259],"iteration":174,"passed_time":0.2276559627,"remaining_time":0.2927005234},
{"learn":[0.3835402178],"iteration":175,"passed_time":0.2290242489,"remaining_time":0.2914854077},
{"learn":[0.3827449845],"iteration":176,"passed_time":0.2303431513,"remaining_time":0.2902063432},
{"learn":[0.3823401514],"iteration":177,"passed_time":0.231735713,"remaining_time":0.2890186982},
{"learn":[0.3814069232],"iteration":178,"passed_time":0.2331237403,"remaining_time":0.2878231654},
{"learn":[0.3806711286],"iteration":179,"passed_time":0.2344034408,"remaining_time":0.2864930943},
{"learn":[0.3794695207],"iteration":180,"passed_time":0.2356669875,"remaining_time":0.2851440346},
{"learn":[0.378956349],"iteration":181,"passed_time":0.2368450819,"remaining_time":0.2836935597},
{"learn":[0.3782115775],"iteration":182,"passed_time":0.2380768578,"remaining_time":0.2823097166},
{"learn":[0.3771382591],"iteration":183,"passed_time":0.2393219083,"remaining_time":0.2809431098},
{"learn":[0.3764628452],"iteration":184,"passed_time":0.2406629898,"remaining_time":0.2796894205},
{"learn":[0.3757521874],"iteration":185,"passed_time":0.2421180925,"remaining_time":0.2785659774},
{"learn":[0.3748602362],"iteration":186,"passed_time":0.2433957237,"remaining_time":0.2772368404},
{"learn":[0.3740541763],"iteration":187,"passed_time":0.2445917914,"remaining_time":0.2758162754},
{"learn":[0.373946551],"iteration":188,"passed_time":0.245040924,"remaining_time":0.2735642061},
{"learn":[0.3732114573],"iteration":189,"passed_time":0.2463294264,"remaining_time":0.2722588398},
{"learn":[0.3727619778],"iteration":190,"passed_time":0.2476048919,"remaining_time":0.2709393844},
{"learn":[0.3723239189],"iteration":191,"passed_time":0.2489150131,"remaining_time":0.2696579308},
{"learn":[0.3716451146],"iteration":192,"passed_time":0.2501951753,"remaining_time":0.2683440482},
{"learn":[0.3709258005],"iteration":193,"passed_time":0.2514762145,"remaining_time":0.2670314443},
{"learn":[0.3701520286],"iteration":194,"passed_time":0.2527074622,"remaining_time":0.2656668192},
{"learn":[0.3693029024],"iteration":195,"passed_time":0.2539933641,"remaining_time":0.2643604401},
{"learn":[0.3690641711],"iteration":196,"passed_time":0.2553053321,"remaining_time":0.263081129},
{"learn":[0.3677525188],"iteration":197,"passed_time":0.2565303148,"remaining_time":0.2617127454},
{"learn":[0.3675968418],"iteration":198,"passed_time":0.257827989,"remaining_time":0.2604192251},
{"learn":[0.3672290803],"iteration":199,"passed_time":0.2591332148,"remaining_time":0.2591332148},
{"learn":[0.3664586884],"iteration":200,"passed_time":0.2601773438,"remaining_time":0.2575885145},
{"learn":[0.3656423367],"iteration":201,"passed_time":0.2616724069,"remaining_time":0.256490775},
{"learn":[0.3651070282],"iteration":202,"passed_time":0.2632170272,"remaining_time":0.2554372136},
{"learn":[0.3642334012],"iteration":203,"passed_time":0.264689095,"remaining_time":0.2543091305},
{"learn":[0.3635209306],"iteration":204,"passed_time":0.2659951645,"remaining_time":0.2530197906},
{"learn":[0.3633788914],"iteration":205,"passed_time":0.2668065165,"remaining_time":0.2512643893},
{"learn":[0.3625562074],"iteration":206,"passed_time":0.2683021848,"remaining_time":0.2501561433},
{"learn":[0.3624405601],"iteration":207,"passed_time":0.2689073923,"remaining_time":0.2482222082},
{"learn":[0.3619297031],"iteration":208,"passed_time":0.2702781763,"remaining_time":0.2470006301},
{"learn":[0.361178418],"iteration":209,"passed_time":0.2716858644,"remaining_time":0.2458110202},
{"learn":[0.3602866072],"iteration":210,"passed_time":0.2731391636,"remaining_time":0.2446601987},
{"learn":[0.359130477],"iteration":211,"passed_time":0.2744328256,"remaining_time":0.2433649586},
{"learn":[0.3584594357],"iteration":212,"passed_time":0.2757722295,"remaining_time":0.2421098916},
{"learn":[0.3577742813],"iteration":213,"passed_time":0.2771526441,"remaining_time":0.2408896813},
{"learn":[0.3568480956],"iteration":214,"passed_time":0.2787137091,"remaining_time":0.2398234241},
{"learn":[0.3562398785],"iteration":215,"passed_time":0.2799778409,"remaining_time":0.2384996422},
{"learn":[0.3555521962],"iteration":216,"passed_time":0.2811889987,"remaining_time":0.2371317362},
{"learn":[0.3550386862],"iteration":217,"passed_time":0.2823993744,"remaining_time":0.2357646154},
{"learn":[0.3544679416],"iteration":218,"passed_time":0.2836741681,"remaining_time":0.2344521663},
{"learn":[0.3538837782],"iteration":219,"passed_time":0.2849871513,"remaining_time":0.2331713056},
{"learn":[0.3533582842],"iteration":220,"passed_time":0.2863098281,"remaining_time":0.2318980056},
{"learn":[0.3529920559],"iteration":221,"passed_time":0.2876657448,"remaining_time":0.2306509125},
{"learn":[0.3529461384],"iteration":222,"passed_time":0.2881057286,"remaining_time":0.2286758474},
{"learn":[0.3518840987],"iteration":223,"passed_time":0.289547243,"remaining_time":0.2275014052},
{"learn":[0.3510349858],"iteration":224,"passed_time":0.2909214812,"remaining_time":0.2262722631},
{"learn":[0.3506495022],"iteration":225,"passed_time":0.2922888952,"remaining_time":0.2250365831},
{"learn":[0.3500893817],"iteration":226,"passed_time":0.2935370681,"remaining_time":0.2237088669},
{"learn":[0.3492607421],"iteration":227,"passed_time":0.2949251141,"remaining_time":0.2224873668},
{"learn":[0.3488064985],"iteration":228,"passed_time":0.2961779141,"remaining_time":0.2211634206},
{"learn":[0.3486137688],"iteration":229,"passed_time":0.2974449354,"remaining_time":0.2198506044},
{"learn":[0.3477004887],"iteration":230,"passed_time":0.2986809509,"remaining_time":0.2185155009},
{"learn":[0.3468889994],"iteration":231,"passed_time":0.2998440973,"remaining_time":0.2171284843},
{"learn":[0.3462063619],"iteration":232,"passed_time":0.3011487154,"remaining_time":0.2158447874},
{"learn":[0.3456604847],"iteration":233,"passed_time":0.3024710916,"remaining_time":0.2145735094},
{"learn":[0.3453794581],"iteration":234,"passed_time":0.3037437504,"remaining_time":0.2132668886},
{"learn":[0.3449011895],"iteration":235,"passed_time":0.3049551341,"remaining_time":0.2119179745},
{"learn":[0.3443994071],"iteration":236,"passed_time":0.3061812424,"remaining_time":0.2105803482},
{"learn":[0.3437383421],"iteration":237,"passed_time":0.3075206293,"remaining_time":0.2093207645},
{"learn":[0.3435732796],"iteration":238,"passed_time":0.30859636,"remaining_time":0.2078829036},
{"learn":[0.3426382023],"iteration":239,"passed_time":0.3098125275,"remaining_time":0.206541685},
{"learn":[0.3419719752],"iteration":240,"passed_time":0.3110370831,"remaining_time":0.2052070382},
{"learn":[0.3413752952],"iteration":241,"passed_time":0.3125660077,"remaining_time":0.2040720216},
{"learn":[0.3407966543],"iteration":242,"passed_time":0.3139921433,"remaining_time":0.2028673518},
{"learn":[0.3400466281],"iteration":243,"passed_time":0.3152914196,"remaining_time":0.2015797601},
{"learn":[0.3395137688],"iteration":244,"passed_time":0.316606368,"remaining_time":0.2003019879},
{"learn":[0.3392348264],"iteration":245,"passed_time":0.3178860061,"remaining_time":0.1990018087},
{"learn":[0.3387969203],"iteration":246,"passed_time":0.3191282722,"remaining_time":0.1976786463},
{"learn":[0.3383068583],"iteration":247,"passed_time":0.320430477,"remaining_time":0.196392873},
{"learn":[0.3380077638],"iteration":248,"passed_time":0.3213311794,"remaining_time":0.1948634863},
{"learn":[0.3372984549],"iteration":249,"passed_time":0.3227372351,"remaining_time":0.193642341},
{"learn":[0.3365261394],"iteration":250,"passed_time":0.3242243067,"remaining_time":0.1924678156},
{"learn":[0.3359700662],"iteration":251,"passed_time":0.3255491735,"remaining_time":0.1911955464},
{"learn":[0.3351382093],"iteration":252,"passed_time":0.3267689483,"remaining_time":0.1898618},
{"learn":[0.3347054248],"iteration":253,"passed_time":0.3279527923,"remaining_time":0.1885082979},
{"learn":[0.3335100427],"iteration":254,"passed_time":0.3294628443,"remaining_time":0.1873416173},
{"learn":[0.3326263779],"iteration":255,"passed_time":0.3307208153,"remaining_time":0.1860304586},
{"learn":[0.332263356],"iteration":256,"passed_time":0.3321117661,"remaining_time":0.1847937064},
{"learn":[0.3320212426],"iteration":257,"passed_time":0.333389433,"remaining_time":0.1834934089},
{"learn":[0.3314592323],"iteration":258,"passed_time":0.3347101557,"remaining_time":0.1822167257},
{"learn":[0.3308161607],"iteration":259,"passed_time":0.3359504299,"remaining_time":0.1808963853},
{"learn":[0.3301427286],"iteration":260,"passed_time":0.3371848787,"remaining_time":0.1795735561},
{"learn":[0.3298704879],"iteration":261,"passed_time":0.3384753119,"remaining_time":0.1782808895},
{"learn":[0.3291144385],"iteration":262,"passed_time":0.3397723429,"remaining_time":0.1769916767},
{"learn":[0.3281772422],"iteration":263,"passed_time":0.341140122,"remaining_time":0.1757388507},
{"learn":[0.3278612432],"iteration":264,"passed_time":0.3424478785,"remaining_time":0.1744545796},
{"learn":[0.3271224092],"iteration":265,"passed_time":0.3436105664,"remaining_time":0.1730970522},
{"learn":[0.3264692099],"iteration":266,"passed_time":0.3447953622,"remaining_time":0.1717519969},
{"learn":[0.3249806896],"iteration":267,"passed_time":0.3459713891,"remaining_time":0.1704038185},
{"learn":[0.3249501595],"iteration":268,"passed_time":0.3464047599,"remaining_time":0.1686952548},
{"learn":[0.3244971953],"iteration":269,"passed_time":0.3476361346,"remaining_time":0.1673803611},
{"learn":[0.3239334885],"iteration":270,"passed_time":0.3488273765,"remaining_time":0.16604698},
{"learn":[0.3226254334],"iteration":271,"passed_time":0.3500906807,"remaining_time":0.1647485556},
{"learn":[0.3219516445],"iteration":272,"passed_time":0.3513948552,"remaining_time":0.1634694015},
{"learn":[0.3211861142],"iteration":273,"passed_time":0.3526911033,"remaining_time":0.1621864198},
{"learn":[0.3205639351],"iteration":274,"passed_time":0.3540310137,"remaining_time":0.160923188},
{"learn":[0.3202417672],"iteration":275,"passed_time":0.3553057372,"remaining_time":0.1596301138},
{"learn":[0.3193651349],"iteration":276,"passed_time":0.3565531404,"remaining_time":0.1583250407},
{"learn":[0.3190393382],"iteration":277,"passed_time":0.3576843835,"remaining_time":0.1569694057},
{"learn":[0.3184776254],"iteration":278,"passed_time":0.358956234,"remaining_time":0.1556763595},
{"learn":[0.3180820809],"iteration":279,"passed_time":0.3602424369,"remaining_time":0.1543896158},
{"learn":[0.3172636182],"iteration":280,"passed_time":0.361634315,"remaining_time":0.1531476281},
{"learn":[0.3167419697],"iteration":281,"passed_time":0.3629025685,"remaining_time":0.1518528478},
{"learn":[0.3162197508],"iteration":282,"passed_time":0.3641879477,"remaining_time":0.1505653353},
{"learn":[0.3157649333],"iteration":283,"passed_time":0.3654841631,"remaining_time":0.1492822638},
{"learn":[0.3154620171],"iteration":284,"passed_time":0.3667636393,"remaining_time":0.1479923457},
{"learn":[0.3148601176],"iteration":285,"passed_time":0.367978971,"remaining_time":0.1466769325},
{"learn":[0.31465308],"iteration":286,"passed_time":0.3692346436,"remaining_time":0.1453781001},
{"learn":[0.3144249751],"iteration":287,"passed_time":0.370476375,"remaining_time":0.1440741458},
{"learn":[0.3137270579],"iteration":288,"passed_time":0.3718359897,"remaining_time":0.1428158992},
{"learn":[0.3131338736],"iteration":289,"passed_time":0.3730732295,"remaining_time":0.1415105353},
{"learn":[0.3125236443],"iteration":290,"passed_time":0.3742928144,"remaining_time":0.1401990267},
{"learn":[0.3119442829],"iteration":291,"passed_time":0.3755236484,"remaining_time":0.1388923083},
{"learn":[0.3116557367],"iteration":292,"passed_time":0.3767294057,"remaining_time":0.1375769502},
{"learn":[0.3108851487],"iteration":293,"passed_time":0.377978731,"remaining_time":0.1362780459},
{"learn":[0.3102881202],"iteration":294,"passed_time":0.3792128193,"remaining_time":0.1349740543},
{"learn":[0.3096611182],"iteration":295,"passed_time":0.3804167818,"remaining_time":0.1336599504},
{"learn":[0.3091624277],"iteration":296,"passed_time":0.3816172972,"remaining_time":0.1323453926},
{"learn":[0.3087520121],"iteration":297,"passed_time":0.3828427963,"remaining_time":0.1310401518},
{"learn":[0.3083682807],"iteration":298,"passed_time":0.3840695626,"remaining_time":0.1297358723},
{"learn":[0.3076145623],"iteration":299,"passed_time":0.3853766624,"remaining_time":0.1284588875},
{"learn":[0.3074083826],"iteration":300,"passed_time":0.3866541612,"remaining_time":0.1271719667},
{"learn":[0.3071156291],"iteration":301,"passed_time":0.3879091639,"remaining_time":0.1258778082},
{"learn":[0.3067083858],"iteration":302,"passed_time":0.3892103371,"remaining_time":0.1245986888},
{"learn":[0.306188973],"iteration":303,"passed_time":0.390515758,"remaining_time":0.1233207657},
{"learn":[0.3058725371],"iteration":304,"passed_time":0.3917998713,"remaining_time":0.1220360255},
{"learn":[0.3056487622],"iteration":305,"passed_time":0.3930391044,"remaining_time":0.1207375027},
{"learn":[0.3051772447],"iteration":306,"passed_time":0.3943027282,"remaining_time":0.1194467548},
{"learn":[0.3047568115],"iteration":307,"passed_time":0.3955522772,"remaining_time":0.1181519789},
{"learn":[0.304099993],"iteration":308,"passed_time":0.3968913553,"remaining_time":0.1168838619},
{"learn":[0.303825131],"iteration":309,"passed_time":0.3981573599,"remaining_time":0.1155940722},
{"learn":[0.3036579222],"iteration":310,"passed_time":0.3992654937,"remaining_time":0.114259257},
{"learn":[0.3036551248],"iteration":311,"passed_time":0.399835421,"remaining_time":0.1127740931},
{"learn":[0.3032530529],"iteration":312,"passed_time":0.4010623581,"remaining_time":0.1114773967},
{"learn":[0.302757443],"iteration":313,"passed_time":0.4023802873,"remaining_time":0.110206066},
{"learn":[0.3024014367],"iteration":314,"passed_time":0.4036369508,"remaining_time":0.1089179074},
{"learn":[0.3019079897],"iteration":315,"passed_time":0.4048804536,"remaining_time":0.1076264497},
{"learn":[0.3015579466],"iteration":316,"passed_time":0.4062767268,"remaining_time":0.1063752944},
{"learn":[0.3007529654],"iteration":317,"passed_time":0.407462894,"remaining_time":0.1050690481},
{"learn":[0.3005272692],"iteration":318,"passed_time":0.4086072561,"remaining_time":0.1037529396},
{"learn":[0.3000537366],"iteration":319,"passed_time":0.4099072954,"remaining_time":0.1024768239},
{"learn":[0.2997144148],"iteration":320,"passed_time":0.4112472404,"remaining_time":0.10121038},
{"learn":[0.2994323869],"iteration":321,"passed_time":0.4125048802,"remaining_time":0.0999235424},
{"learn":[0.2989877549],"iteration":322,"passed_time":0.4137353622,"remaining_time":0.09863041142},
{"learn":[0.2984794569],"iteration":323,"passed_time":0.4150079679,"remaining_time":0.09734754802},
{"learn":[0.2979217974],"iteration":324,"passed_time":0.4163045867,"remaining_time":0.09607028925},
{"learn":[0.2976302583],"iteration":325,"passed_time":0.417452277,"remaining_time":0.09475910581},
{"learn":[0.2974459547],"iteration":326,"passed_time":0.4187017262,"remaining_time":0.09347163917},
{"learn":[0.2971540263],"iteration":327,"passed_time":0.4199349727,"remaining_time":0.09218084767},
{"learn":[0.2969564889],"iteration":328,"passed_time":0.4211558197,"remaining_time":0.09088773009},
{"learn":[0.2966480575],"iteration":329,"passed_time":0.4225518926,"remaining_time":0.08963221964},
{"learn":[0.2961073873],"iteration":330,"passed_time":0.4240034826,"remaining_time":0.08838743293},
{"learn":[0.295774084],"iteration":331,"passed_time":0.4254462237,"remaining_time":0.08713958799},
{"learn":[0.29528236],"iteration":332,"passed_time":0.4267328219,"remaining_time":0.08585915635},
{"learn":[0.2943887334],"iteration":333,"passed_time":0.4279742956,"remaining_time":0.08456977099},
{"learn":[0.2939428677],"iteration":334,"passed_time":0.429253899,"remaining_time":0.08328806996},
{"learn":[0.2935074488],"iteration":335,"passed_time":0.4305526308,"remaining_time":0.08201002491},
{"learn":[0.2931150531],"iteration":336,"passed_time":0.4318780272,"remaining_time":0.08073684189},
{"learn":[0.2923170394],"iteration":337,"passed_time":0.4331132063,"remaining_time":0.07944680115},
{"learn":[0.2921461999],"iteration":338,"passed_time":0.4343844238,"remaining_time":0.07816356889},
{"learn":[0.2912731588],"iteration":339,"passed_time":0.4356127548,"remaining_time":0.07687283909},
{"learn":[0.2907986246],"iteration":340,"passed_time":0.4369186482,"remaining_time":0.07559589515},
{"learn":[0.2901185112],"iteration":341,"passed_time":0.4383099979,"remaining_time":0.0743332745},
{"learn":[0.2895448222],"iteration":342,"passed_time":0.4394889248,"remaining_time":0.07303460267},
{"learn":[0.2891153051],"iteration":343,"passed_time":0.4406841497,"remaining_time":0.07173928019},
{"learn":[0.2886131],"iteration":344,"passed_time":0.4419151701,"remaining_time":0.07045024452},
{"learn":[0.2882856526],"iteration":345,"passed_time":0.4431680151,"remaining_time":0.06916495033},
{"learn":[0.2879373813],"iteration":346,"passed_time":0.4444418454,"remaining_time":0.06788304844},
{"learn":[0.2876093658],"iteration":347,"passed_time":0.445664941,"remaining_time":0.06659361188},
{"learn":[0.2871527098],"iteration":348,"passed_time":0.4470727129,"remaining_time":0.06533154257},
{"learn":[0.2868296537],"iteration":349,"passed_time":0.4482851913,"remaining_time":0.06404074161},
{"learn":[0.2866529797],"iteration":350,"passed_time":0.4495780694,"remaining_time":0.06276161083},
{"learn":[0.2863263497],"iteration":351,"passed_time":0.4508690944,"remaining_time":0.06148214924},
{"learn":[0.2861480653],"iteration":352,"passed_time":0.4521554381,"remaining_time":0.06020199884},
{"learn":[0.2857253482],"iteration":353,"passed_time":0.4535781849,"remaining_time":0.05893953815},
{"learn":[0.2850253416],"iteration":354,"passed_time":0.4549404264,"remaining_time":0.05766850476},
{"learn":[0.2846110315],"iteration":355,"passed_time":0.4562429359,"remaining_time":0.05638957634},
{"learn":[0.2835640221],"iteration":356,"passed_time":0.4574420916,"remaining_time":0.05509806706},
{"learn":[0.2829769477],"iteration":357,"passed_time":0.4586617643,"remaining_time":0.05380948073},
{"learn":[0.2827506973],"iteration":358,"passed_time":0.4601126223,"remaining_time":0.0525476811},
{"learn":[0.2824669609],"iteration":359,"passed_time":0.4613576617,"remaining_time":0.05126196241},
{"learn":[0.2823971093],"iteration":360,"passed_time":0.462779295,"remaining_time":0.04999554711},
{"learn":[0.2821287255],"iteration":361,"passed_time":0.4640152532,"remaining_time":0.04870878349},
{"learn":[0.2818980936],"iteration":362,"passed_time":0.4654232249,"remaining_time":0.04743983284},
{"learn":[0.2815339559],"iteration":363,"passed_time":0.4666379262,"remaining_time":0.04615100369},
{"learn":[0.2809261099],"iteration":364,"passed_time":0.4679070548,"remaining_time":0.04486779978},
{"learn":[0.2804925303],"iteration":365,"passed_time":0.469170263,"remaining_time":0.04358412279},
{"learn":[0.2801957015],"iteration":366,"passed_time":0.4704027963,"remaining_time":0.04229779912},
{"learn":[0.2797934128],"iteration":367,"passed_time":0.4716157671,"remaining_time":0.04101006671},
{"learn":[0.2791118786],"iteration":368,"passed_time":0.4731653038,"remaining_time":0.03975101468},
{"learn":[0.2782029809],"iteration":369,"passed_time":0.4745604296,"remaining_time":0.03847787267},
{"learn":[0.2773291168],"iteration":370,"passed_time":0.4757870773,"remaining_time":0.03719090362},
{"learn":[0.2769087329],"iteration":371,"passed_time":0.4771693828,"remaining_time":0.03591597505},
{"learn":[0.2765105909],"iteration":372,"passed_time":0.478682589,"remaining_time":0.03464994612},
{"learn":[0.2759628293],"iteration":373,"passed_time":0.4799462495,"remaining_time":0.03336524729},
{"learn":[0.2754529678],"iteration":374,"passed_time":0.4813110056,"remaining_time":0.03208740037},
{"learn":[0.2750843158],"iteration":375,"passed_time":0.4825526924,"remaining_time":0.03080123568},
{"learn":[0.2747743105],"iteration":376,"passed_time":0.4838136277,"remaining_time":0.02951648127},
{"learn":[0.2743949999],"iteration":377,"passed_time":0.4850856204,"remaining_time":0.02823249643},
{"learn":[0.2742691896],"iteration":378,"passed_time":0.4862724388,"remaining_time":0.02694385545},
{"learn":[0.273893871],"iteration":379,"passed_time":0.4874517167,"remaining_time":0.02565535351},
{"learn":[0.2729707709],"iteration":380,"passed_time":0.4887141827,"remaining_time":0.02437157341},
{"learn":[0.2727909485],"iteration":381,"passed_time":0.4900688025,"remaining_time":0.02309224724},
{"learn":[0.2721919827],"iteration":382,"passed_time":0.4913202064,"remaining_time":0.0218079465},
{"learn":[0.2717060397],"iteration":383,"passed_time":0.4929816071,"remaining_time":0.0205409003},
{"learn":[0.2712966958],"iteration":384,"passed_time":0.4943360787,"remaining_time":0.01925984722},
{"learn":[0.2707655757],"iteration":385,"passed_time":0.4956482431,"remaining_time":0.01797687928},
{"learn":[0.2700968454],"iteration":386,"passed_time":0.4969638636,"remaining_time":0.01669387656},
{"learn":[0.2695600211],"iteration":387,"passed_time":0.4982310443,"remaining_time":0.01540920756},
{"learn":[0.2693155372],"iteration":388,"passed_time":0.4995096987,"remaining_time":0.01412495292},
{"learn":[0.2687950249],"iteration":389,"passed_time":0.500805252,"remaining_time":0.01284116031},
{"learn":[0.2683656768],"iteration":390,"passed_time":0.5021092389,"remaining_time":0.01155750166},
{"learn":[0.2681236983],"iteration":391,"passed_time":0.5032746189,"remaining_time":0.01027091059},
{"learn":[0.2680279894],"iteration":392,"passed_time":0.5046402117,"remaining_time":0.008988502499},
{"learn":[0.2671432911],"iteration":393,"passed_time":0.5061243278,"remaining_time":0.007707477073},
{"learn":[0.2663299106],"iteration":394,"passed_time":0.5073946966,"remaining_time":0.006422717679},
{"learn":[0.2661118854],"iteration":395,"passed_time":0.5086767794,"remaining_time":0.005138149287},
{"learn":[0.2657023958],"iteration":396,"passed_time":0.5100372923,"remaining_time":0.003854186088},
{"learn":[0.265541514],"iteration":397,"passed_time":0.5114841376,"remaining_time":0.002570272048},
{"learn":[0.2652581683],"iteration":398,"passed_time":0.5130296743,"remaining_time":0.001285788657},
{"learn":[0.2648413037],"iteration":399,"passed_time":0.5144073488,"remaining_time":0}
]}